cafle/__init__.py
cafle/account.py
cafle/genfunc.py
cafle/index.py
cafle/write.py
cafle-1.0.1.dist-info/LICENSE
cafle-1.0.1.dist-info/METADATA
cafle-1.0.1.dist-info/WHEEL
cafle-1.0.1.dist-info/top_level.txt
cafle-1.0.1.dist-info/RECORD
