Metadata-Version: 2.1
Name: cafle
Version: 1.0.1
Summary: a cash flow estimating tool
Home-page: https://github.com/kphong16
Author: kphong
Author-email: kphong16@daum.net
Project-URL: Bug Tracker, https://github.com/kphong16
Classifier: Programming Language :: Python :: 3
Classifier: License :: OSI Approved :: GNU General Public License v3 (GPLv3)
Classifier: Operating System :: OS Independent
Requires-Python: >=3.6
License-File: LICENSE
Requires-Dist: pandas>=2.0
Requires-Dist: numpy
Requires-Dist: xlsxwriter
